monarch_py/__init__.py
monarch_py/cli.py
monarch_py/solr_cli.py
monarch_py/sql_cli.py
monarch_py/api/__init__.py
monarch_py/api/additional_models.py
monarch_py/api/association.py
monarch_py/api/config.py
monarch_py/api/entity.py
monarch_py/api/histopheno.py
monarch_py/api/main.py
monarch_py/api/search.py
monarch_py/api/semsim.py
monarch_py/api/text_annotation.py
monarch_py/api/middleware/__init__.py
monarch_py/api/middleware/logging_middleware.py
monarch_py/api/utils/__init__.py
monarch_py/api/utils/similarity_utils.py
monarch_py/datamodels/__init__.py
monarch_py/datamodels/category_enums.py
monarch_py/datamodels/model.py
monarch_py/datamodels/model.yaml
monarch_py/datamodels/similarity.yaml
monarch_py/datamodels/solr.py
monarch_py/implementations/__init__.py
monarch_py/implementations/oak/annotation_utils.py
monarch_py/implementations/oak/oak_implementation.py
monarch_py/implementations/solr/__init__.py
monarch_py/implementations/solr/solr_implementation.py
monarch_py/implementations/solr/solr_parsers.py
monarch_py/implementations/solr/solr_query_utils.py
monarch_py/implementations/spacy/spacy_implementation.py
monarch_py/implementations/sql/__init__.py
monarch_py/implementations/sql/sql_implementation.py
monarch_py/interfaces/__init__.py
monarch_py/interfaces/association_interface.py
monarch_py/interfaces/entity_interface.py
monarch_py/interfaces/grounding_interface.py
monarch_py/interfaces/mapping_interface.py
monarch_py/interfaces/query_interface.py
monarch_py/interfaces/search_interface.py
monarch_py/interfaces/text_annotation_interface.py
monarch_py/service/__init__.py
monarch_py/service/curie_service.py
monarch_py/service/semsim_service.py
monarch_py/service/solr_service.py
monarch_py/utils/__init__.py
monarch_py/utils/association_type_mappings.yaml
monarch_py/utils/association_type_utils.py
monarch_py/utils/cli_fields.py
monarch_py/utils/entity_utils.py
monarch_py/utils/format_utils.py
monarch_py/utils/solr_cli_utils.py
monarch_py/utils/utils.py
monarch_py-1.24.0.dist-info/METADATA
monarch_py-1.24.0.dist-info/WHEEL
monarch_py-1.24.0.dist-info/entry_points.txt
monarch_py-1.24.0.dist-info/RECORD
