Metadata-Version: 2.4
Name: monarch-py
Version: 1.24.0
Summary: Python package for interacting with Monarch Initiative knowledge graph
Author-email: The Monarch Initiative <info@monarchinitiative.org>, kevin schaper <kevin@tislab.org>, glass-ships <glass.ships@outlook.com>
Requires-Python: <4.0,>=3.10
Requires-Dist: beautifulsoup4>=4.13.4
Requires-Dist: bioregistry~=0.10.57
Requires-Dist: curies<1
Requires-Dist: docker>=7.1.0
Requires-Dist: fastapi<1,>=0.115.12
Requires-Dist: gunicorn>=23.0.0
Requires-Dist: linkml==1.9.3
Requires-Dist: loguru
Requires-Dist: oaklib>=0.6.6
Requires-Dist: prefixmaps==0.2.4
Requires-Dist: pydantic<3,>=2
Requires-Dist: pystow>=0.5.4
Requires-Dist: requests>=2.31.0
Requires-Dist: rich
Requires-Dist: spacy>=3.8.7
Requires-Dist: typer>=0.12.0
Provides-Extra: dev
Requires-Dist: black>=24.4.2; extra == 'dev'
Requires-Dist: coverage>=7.5.1; extra == 'dev'
Requires-Dist: httpx>=0.27; extra == 'dev'
Requires-Dist: mkdocs-material>=9.5.23; extra == 'dev'
Requires-Dist: mkdocs>=1.6.0; extra == 'dev'
Requires-Dist: mkdocstrings[python]>=0.29.1; extra == 'dev'
Requires-Dist: pytest>=8.2.0; extra == 'dev'
Requires-Dist: ruff; extra == 'dev'
Requires-Dist: scholarly; extra == 'dev'
Requires-Dist: uvicorn[standard]>=0.29.0; extra == 'dev'
